{"id":12380,"name":"Add new rows to Google BigQuery from a custom webhook","description":"Streamline your data management process by automatically adding new entries to Google BigQuery whenever a custom webhook is triggered. This template allows you to efficiently capture and store data from various sources, ensuring that your analytics and reporting are always up-to-date. Perfect for developers and data analysts looking to enhance their data workflows without manual intervention.","url":"12380-add-new-rows-to-google-bigquery-from-a-custom-webhook","usedApps":["gateway","google-bigquery"],"usage":13}