{"id":8177,"name":"Create a new record in Airtable from a new project event in QuickCapture","description":"Every time a new event appears in your project in QuickCapture, a new record will be instantly added in Airtable.\n\nThis template is using a sample \"Occupancy Counter\" project mentioned in this [article.](https://storymaps.arcgis.com/stories/17035aed761d4dd6bd934eb72f81586e)\n\nOur sample Airtable has these columns:\n1) User Full Name as text\n2) Project Title as text\n3) Site as text\n4) User Email as text\n5) Geometry X as text\n6) Geometry Y as text\n7) Tally as number\n\nYou can use a different project and a different Airtable schema with this template but you will need to edit mappings in the Airtable module.","url":"8177-create-a-new-record-in-airtable-from-a-new-project-event-in-quickcapture","usedApps":["quickcapture","airtable"],"usage":2}