{"id":12394,"name":"Create Google Calendar events from Clockify time entries","description":"Streamline your time management by automatically creating events in Google Calendar whenever a new time entry is logged in Clockify. This template ensures that all your tracked hours are seamlessly reflected in your calendar, helping you stay organized and on top of your schedule. Perfect for professionals who want to enhance their productivity and maintain a clear overview of their time commitments.","url":"12394-create-google-calendar-events-from-clockify-time-entries","usedApps":["clockify","google-calendar"],"usage":69}