{"id":7254,"name":"Create a new databse item in Notion from new actions in Glide","description":"Every time a new action happens in Glide, a new database item will be instantly created in Notion.\n\nThe template is creating a list of users in Notion so it expects to receive at least user emails under a \"current_user\" variable - make sure it's called exactly the same in your Glide webhook otherwise you will have to map a different variable during the template setup.\n\nThe template also expects to have an \"Email\" column in your Notion database.","url":"7254-create-a-new-databse-item-in-notion-from-new-actions-in-glide","usedApps":["glide","notion"],"usage":51}