{"id":13314,"name":"Get Business Data for Salesforce leads with DataForSEO","description":"Automatically enrich your Salesforce leads with comprehensive business details from Google using DataForSEO API and Make. Effortlessly access critical information such as business name, description, categories, rating, address and contact details, and more. Use these insights to personalize your outreach, optimize campaigns, and make data-driven decisions. To get started, check our [Setup Guide for First Use](https://docs.google.com/document/d/1aziLp2qnouZ6b9s8KlTmTJ-R86zNemjmOyCHH47lSJc/edit?usp=sharing).","url":"13314-salesforce-business-data","usedApps":["salesforce","dataforseo"],"usage":16}