{"id":3222,"name":"Insert new rows with data from Google Sheets to a location specified by index in a document in Google Docs","description":"When new rows are added to Google Sheets spreadsheet, the corresponding data are sent as new rows to Google Docs document. Here, you can specify the start of a list by index, so the newest rows appear as first.","url":"3222-insert-new-rows-with-data-from-google-sheets-to-a-location-specified-by-index-in-a-document-in-google-docs","usedApps":["google-sheets","util","google-docs"],"usage":499}