{"id":12326,"name":"Send an email with Microsoft Excel workbook as an attachment","description":"Streamline your communication process by automatically sending emails based on data from your Microsoft Excel workbook. This template allows you to extract information from your Excel files and create personalized email messages using Microsoft Email, ensuring that your outreach is efficient and data-driven. Perfect for managing contacts, sending updates, or following up on important tasks, this integration saves you time and enhances your productivity.","url":"12326-send-an-email-with-microsoft-excel-workbook-as-an-attachment","usedApps":["microsoft-excel","microsoft-email"],"usage":447}