{"id":12316,"name":"Send an email notification for new features in ArcGIS Field Maps","description":"Streamline your field operations by automatically sending email notifications whenever a new feature is added to your ArcGIS Field Maps. This template connects ArcGIS Field Maps with Microsoft Email, ensuring that your team stays informed and responsive to changes in real-time. With this integration, you can enhance communication and improve project management efficiency, allowing you to focus on what matters most.","url":"12316-send-an-email-notification-for-new-features-in-arcgis-field-maps","usedApps":["arcgis-field-maps","microsoft-email"],"usage":31}