{"id":12770,"name":"Send data to an HTTP endpoint for every new email in Gmail","description":"Streamline your email management process by automatically sending data from new emails in Google Gmail to your desired endpoint using HTTP. This template ensures that every time you receive a new email, relevant information is instantly transmitted, enhancing your workflow efficiency and allowing for better data handling. Perfect for users looking to integrate their email communications with other applications seamlessly.","url":"12359-send-data-to-an-http-endpoint-for-every-new-email-in-gmail","usedApps":["google-email","http"],"usage":26}