{"id":10408,"name":"Transcribe audio file and analyze sentiment with Eden AI PART 1","description":"Use this template to transcript audio data from Google Drive into Eden AI Speech-to-text module. Then extract sentiment from text transcripted. Datastore module is used to wait until the transcription is finished. Please see Speech-to-text + Sentiment Analysis PART 2 template.\nCreated by tech@edenai.co","url":"10408-transcribe-audio-file-and-analyze-sentiment-with-eden-ai-part-1","usedApps":["google-drive","edenai","util","builtin","google-sheets","datastore"],"usage":65}